pyfsa/__init__.py
pyfsa/__init__.pyi
pyfsa/main.py
pyfsa/main.pyi
pyfsa/py.typed
pyfsa/lib/__init__.py
pyfsa/lib/__init__.pyi
pyfsa/lib/csv_convert.py
pyfsa/lib/csv_convert.pyi
pyfsa/lib/fsa.py
pyfsa/lib/fsa.pyi
pyfsa/lib/types.py
pyfsa/lib/types.pyi
pyfsa-0.4.1.dist-info/LICENSE
pyfsa-0.4.1.dist-info/METADATA
pyfsa-0.4.1.dist-info/WHEEL
pyfsa-0.4.1.dist-info/entry_points.txt
pyfsa-0.4.1.dist-info/top_level.txt
pyfsa-0.4.1.dist-info/RECORD
